{
  "te": [
    {
      "name": "はけません",
      "romaji": "haikemasen"
    },
    {
      "name": "もいいですか",
      "romaji": "moidesuka"
    },
    {
      "name": "ください",
      "romaji": "kudasai"
    },
    {
      "name": "いる",
      "romaji": "iru"
    },
    {
      "name": "しまう",
      "romaji": "shimau"
    },
    {
      "name": "みる",
      "romaji": "miru"
    },
    {
      "name": "あげる",
      "romaji": "ageru"
    },
    {
      "name": "もらう",
      "romaji": "morau"
    },
    {
      "name": "から",
      "romaji": "kara"
    },
    {
      "name": "おく",
      "romaji": "oku"
    }
  ],
  "ta":[
    {
      "name": "ことがある",
      "romaji": "kotogaaru"
    },
    {
      "name": "ばかり",
      "romaji": "bakari"
    },
    {
      "name": "り,たりする",
      "romaji": "ritarisuru"
    },
    {
      "name": "ら",
      "romaji": "ra"
    },
    {
      "name": "ほうがいい",
      "romaji": "hougaii"
    },
    {
      "name": "のに",
      "romaji": "noni"
    },
    {
      "name": "まま",
      "romaji": "mama"
    },
    {
      "name": "らどうか",
      "romaji": "radouka"
    }
  ],
  "nai":[
    {
      "name": "ければならない",
      "romaji": "kerebanaranai"
    },
    {
      "name": "いでください",
      "romaji": "idekudasai"
    },
    {
      "name": "いほうがいい",
      "romaji": "ihougaii"
    },
    {
      "name": "くてもいい",
      "romaji": "kutemoii"
    },
    {
      "name": "くなる",
      "romaji": "kunaru"
    },
    {
      "name": "ずに",
      "romaji": "zuni"
    },
    {
      "name": "いうちに",
      "romaji": "iuchini"
    },
    {
      "name": "いかぎり",
      "romaji": "ikagiri"
    },
    {
      "name": "くてはならない",
      "romaji": "kutehanaranai"
    },
    {
      "name": "いようにする",
      "romaji": "iyounisuru"
    }
  ],
  "ru":[
    {
      "name": "ことがある",
      "romaji": "kotogaaru"
    },
    {
      "name": "ことができる",
      "romaji": "kotogadekiru"
    },
    {
      "name": "つもり",
      "romaji": "tsumori"
    },
    {
      "name": "ために",
      "romaji": "tameni"
    },
    {
      "name": "ようになる",
      "romaji": "youninaru"
    },
    {
      "name": "ところ",
      "romaji": "tokoro"
    },
    {
      "name": "ようにする",
      "romaji": "younisuru"
    },
    {
      "name": "べきだ",
      "romaji": "bekida"
    },
    {
      "name": "かもしれない",
      "romaji": "kamoshirenai"
    },
    {
      "name": "まえに",
      "romaji": "maeni"
    }
  ],
  "masu":[
    {
      "name": "す",
      "romaji": "su"
    },
    {
      "name": "せん",
      "romaji": "sen"
    },
    {
      "name": "した",
      "romaji": "shita"
    },
    {
      "name": "せんでした",
      "romaji": "sendeshita"
    }
  ]
}
